ado_actuators/sfttrainer/README.md
ado_actuators/sfttrainer/UPDATE_PROTOCOL.md
ado_actuators/sfttrainer/__init__.py
ado_actuators/sfttrainer/actuator_definitions.yaml
ado_actuators/sfttrainer/actuators.py
ado_actuators/sfttrainer/config/map_version_to_commit.yaml
ado_actuators/sfttrainer/config/models.yaml
ado_actuators/sfttrainer/experiments/__init__.py
ado_actuators/sfttrainer/experiments/common.py
ado_actuators/sfttrainer/experiments/full_finetune.py
ado_actuators/sfttrainer/experiments/gptq_lora.py
ado_actuators/sfttrainer/experiments/lora.py
ado_actuators/sfttrainer/experiments/prompt_tuning.py
ado_actuators/sfttrainer/packages/fms-hf-tuning_v2.0.1_9b8245e74144f7ee73b7241a1687b6c77f0eb2e4.txt
ado_actuators/sfttrainer/packages/fms-hf-tuning_v2.1.0_8f168183a70b41cb66902f438ecba7734144138c.txt
ado_actuators/sfttrainer/packages/fms-hf-tuning_v2.1.1_e2ac09183d8ba29084e110fd16b6b6c872e4a267.txt
ado_actuators/sfttrainer/packages/fms-hf-tuning_v2.1.2_1e82e020f64d5a53acf98eecccb33c3597881b5e.txt
ado_actuators/sfttrainer/packages/fms-hf-tuning_v2.2.1_e6f7a2205c06e703c6b22bdcc5e1f248823c2a2e.txt
ado_actuators/sfttrainer/packages/fms-hf-tuning_v2.3.1_3ec30a0f9c47b0b6b9f43ce9200ab4ff24ed01e8.txt
ado_actuators/sfttrainer/packages/fms-hf-tuning_v2.4.0_76bd76d0cfef0852e8490c344b791a35a1080ead.txt
ado_actuators/sfttrainer/packages/fms-hf-tuning_v2.5.0_6f9bab223987732826f625fc7a522a78b58697fb.txt
ado_actuators/sfttrainer/packages/fms-hf-tuning_v2.6.0_53f2babaddf07c85f5274167af9aaa947f19faf3.txt
ado_actuators/sfttrainer/packages/fms-hf-tuning_v2.7.1_456fe2a840e7f0b2d8d48c04cefe24faddbf261a.txt
ado_actuators/sfttrainer/packages/fms-hf-tuning_v2.8.2_ad594c7270e934679d48286aa87c5ade7bfc54e2.txt
ado_actuators/sfttrainer/packages/fms-hf-tuning_v3.0.0.1_51875160343064a1056e0105b7971ed8d9f26854.txt
ado_actuators/sfttrainer/packages/fms-hf-tuning_v3.0.0_d8cb1cbacfbab7ed23e91151f59516766ab339e2.txt
ado_sfttrainer-1.4.1.dist-info/METADATA
ado_sfttrainer-1.4.1.dist-info/WHEEL
ado_sfttrainer-1.4.1.dist-info/entry_points.txt
ado_sfttrainer-1.4.1.dist-info/top_level.txt
ado_sfttrainer-1.4.1.dist-info/RECORD
