Metadata-Version: 2.4
Name: ado-sfttrainer
Version: 1.4.1
Summary: An actuator for benchmarking fine-tuning of foundation models
Requires-Python: <3.13,>=3.10
Requires-Dist: jwt
Requires-Dist: aim>=3.23.0
Requires-Dist: transformers>=4.44.2
Requires-Dist: psutil
